workflow/__init__.py
workflow/config.py
workflow/deprecation.py
workflow/engine.py
workflow/engine_db.py
workflow/errors.py
workflow/signals.py
workflow/utils.py
workflow/version.py
workflow/patterns/__init__.py
workflow/patterns/controlflow.py
workflow/patterns/utils.py
workflow-2.1.5.data/scripts/run_workflow.py
workflow-2.1.5.dist-info/METADATA
workflow-2.1.5.dist-info/RECORD
workflow-2.1.5.dist-info/WHEEL
workflow-2.1.5.dist-info/top_level.txt
